polars_business-0.3.22.dist-info/METADATA
polars_business-0.3.22.dist-info/WHEEL
polars_business-0.3.22.dist-info/license_files/LICENSE
polars_business/ranges.py
polars_business/__init__.py
polars_business/py.typed
polars_business/polars_business.cpython-311-s390x-linux-gnu.so
polars_business-0.3.22.dist-info/RECORD
