Metadata-Version: 2.1
Name: polars-business
Version: 0.3.22
Classifier: Programming Language :: Rust
Classifier: Programming Language :: Python :: Implementation :: CPython
Classifier: Programming Language :: Python :: Implementation :: PyPy
License-File: LICENSE
Summary: Business day utilities for Polars
Author-email: Marco Gorelli <33491632+MarcoGorelli@users.noreply.github.com>
Requires-Python: >=3.8
